setnacki/__init__.py
setnacki/game/__init__.py
setnacki/game/engine.py
setnacki/game/players.py
setnacki/game/renderers.py
setnacki/game/setback_mini.py
setnacki/logic/__init__.py
setnacki/logic/exceptions.py
setnacki/logic/models.py
setnacki/logic/sim_runner_strategies.py
setnacki/logic/validators.py
setnacki/logic/bid_models/__init__.py
setnacki/logic/bid_models/one_suit_min_14.py
setnacki/logic/play_models/__init__.py
setnacki-0.0.2.dist-info/METADATA
setnacki-0.0.2.dist-info/WHEEL
setnacki-0.0.2.dist-info/top_level.txt
setnacki-0.0.2.dist-info/RECORD
